schelling_model/__init__.py
schelling_model/schelling_model.py
schelling_model-0.0.1.dist-info/METADATA
schelling_model-0.0.1.dist-info/WHEEL
schelling_model-0.0.1.dist-info/top_level.txt
schelling_model-0.0.1.dist-info/RECORD
