Metadata-Version: 2.1
Name: schelling-model
Version: 0.0.1
Summary: Schelling model of neightbours segregation
Author: quim
Author-email: <quimort97@gmail.com>
Keywords: python,schelling,segregation
Classifier: Development Status :: 1 - Planning
Classifier: Intended Audience :: Developers
Classifier: Programming Language :: Python :: 3
Classifier: Operating System :: Unix
Classifier: Operating System :: MacOS :: MacOS X
Classifier: Operating System :: Microsoft :: Windows
Requires-Dist: numpy
Requires-Dist: scipy
